{
  "config": {
    "step": {
      "user": {
        "title": "Frigate connection",
        "description": "Enter your Frigate server details. Fields are pre-filled if the Frigate integration is installed.",
        "data": {
          "url": "Frigate URL",
          "username": "Username (optional)",
          "password": "Password (optional)"
        }
      },
      "notify": {
        "title": "Default notification",
        "description": "Select the default notification service. You can override it per camera.",
        "data": {
          "notify_target": "Notification service"
        }
      }
    },
    "error": {
      "cannot_connect": "Cannot connect to Frigate. Check the URL and credentials."
    },
    "abort": {
      "already_configured": "Frigate Event Manager is already configured.",
      "reconfigure_successful": "Configuration updated successfully."
    }
  },
  "config_subentries": {
    "camera": {
      "entry_type": "Camera",
      "initiate_flow": {
        "user": "Add camera"
      },
      "step": {
        "user": {
          "title": "Add a camera",
          "description": "Select a camera from your Frigate instance.",
          "data": {
            "camera": "Camera",
            "notify_target": "Notification service"
          }
        },
        "reconfigure": {
          "title": "Edit camera",
          "data": {
            "notify_target": "Notification service"
          }
        }
      },
      "error": {
        "cannot_connect": "Cannot connect to Frigate. Check the URL and credentials."
      },
      "abort": {
        "no_cameras_available": "All cameras are already configured.",
        "reconfigure_successful": "Camera updated successfully."
      }
    }
  },
  "reconfigure": {
    "step": {
      "reconfigure": {
        "title": "Edit Frigate connection",
        "data": {
          "url": "Frigate URL",
          "username": "Username (optional)",
          "password": "Password (optional)",
          "notify_target": "Default notification service"
        }
      }
    },
    "error": {
      "cannot_connect": "Cannot connect to Frigate. Check the URL and credentials."
    },
    "abort": {
      "reconfigure_successful": "Configuration updated successfully."
    }
  },
  "entity": {
    "switch": {
      "notifications": {
        "name": "Notifications"
      }
    },
    "binary_sensor": {
      "mouvement": {
        "name": "Motion"
      }
    }
  }
}
